replay_classification/__init__.py
replay_classification/core.py
replay_classification/decoders.py
replay_classification/initial_conditions.py
replay_classification/misc.py
replay_classification/multiunit.py
replay_classification/simulate.py
replay_classification/sorted_spikes.py
replay_classification/state_transition.py
replay_classification-0.6.1.dist-info/LICENSE
replay_classification-0.6.1.dist-info/METADATA
replay_classification-0.6.1.dist-info/WHEEL
replay_classification-0.6.1.dist-info/top_level.txt
replay_classification-0.6.1.dist-info/RECORD
