Metadata-Version: 2.1
Name: replay-classification
Version: 0.6.1
Summary: Non-parametric categorization of replay content from multiunit spiking activity
Home-page: https://github.com/Eden-Kramer-Lab/replay_classification
Author: Eric Denovellis
Author-email: edeno@bu.edu
License: GPL-3.0
Platform: UNKNOWN
Requires-Dist: numpy (>=1.11)
Requires-Dist: pandas (>=0.18.0)
Requires-Dist: scipy
Requires-Dist: xarray
Requires-Dist: statsmodels
Requires-Dist: matplotlib
Requires-Dist: numba
Requires-Dist: patsy
Requires-Dist: seaborn
Requires-Dist: holoviews
Requires-Dist: bokeh
Requires-Dist: regularized-glm
Requires-Dist: scikit-learn
